flowlite/__init__.py
flowlite/autograd.py
flowlite/backend_numpy.py
flowlite/optim.py
flowlite/data/__init__.py
flowlite/data/data_basic.py
flowlite/data/data_transforms.py
flowlite/data/datasets/__init__.py
flowlite/data/datasets/mnist_dataset.py
flowlite/data/datasets/ndarray_dataset.py
flowlite/init/__init__.py
flowlite/init/init_basic.py
flowlite/init/init_initializer.py
flowlite/nn/__init__.py
flowlite/nn/nn_basic.py
flowlite/ops/__init__.py
flowlite/ops/ops_logarithmic.py
flowlite/ops/ops_mathematic.py
flowlite-0.0.3.dist-info/LICENSE
flowlite-0.0.3.dist-info/METADATA
flowlite-0.0.3.dist-info/WHEEL
flowlite-0.0.3.dist-info/top_level.txt
flowlite-0.0.3.dist-info/RECORD
