Metadata-Version: 2.1
Name: flowlite
Version: 0.0.3
Summary: A simple, educational deep learning framework
Home-page: https://github.com/caaatch22/flowlite
Author: Mingjie
Author-email: <mr.liumingjie@gmail.com>
License: UNKNOWN
Keywords: deep learning,auto-diff
Platform: UNKNOWN
Classifier: Intended Audience :: Developers
Classifier: Programming Language :: Python :: 3
Classifier: Operating System :: Unix
Classifier: Operating System :: MacOS :: MacOS X
Classifier: Operating System :: Microsoft :: Windows
License-File: LICENSE
Requires-Dist: numpy
